Metadata-Version: 1.0
Name: pymcda
Version: 0.4
Summary: mcda in pure python
Home-page: https://github.com/gmassei/pymcda
Author: gianluca massei
Author-email: g_massa@libero.it
License: GPL
Platform: UNKNOWN
